oscura/__init__.py
oscura/__main__.py
oscura/convenience.py
oscura/py.typed
oscura/analyzers/__init__.py
oscura/analyzers/classification.py
oscura/analyzers/entropy.py
oscura/analyzers/measurements.py
oscura/analyzers/validation.py
oscura/analyzers/digital/__init__.py
oscura/analyzers/digital/bus.py
oscura/analyzers/digital/clock.py
oscura/analyzers/digital/correlation.py
oscura/analyzers/digital/edges.py
oscura/analyzers/digital/extraction.py
oscura/analyzers/digital/quality.py
oscura/analyzers/digital/signal_quality.py
oscura/analyzers/digital/thresholds.py
oscura/analyzers/digital/timing.py
oscura/analyzers/digital/timing_numba.py
oscura/analyzers/eye/__init__.py
oscura/analyzers/eye/diagram.py
oscura/analyzers/eye/generation.py
oscura/analyzers/eye/metrics.py
oscura/analyzers/jitter/__init__.py
oscura/analyzers/jitter/ber.py
oscura/analyzers/jitter/classification.py
oscura/analyzers/jitter/decomposition.py
oscura/analyzers/jitter/measurements.py
oscura/analyzers/jitter/spectrum.py
oscura/analyzers/jitter/timing.py
oscura/analyzers/ml/__init__.py
oscura/analyzers/ml/features.py
oscura/analyzers/ml/signal_classifier.py
oscura/analyzers/packet/__init__.py
oscura/analyzers/packet/daq.py
oscura/analyzers/packet/metrics.py
oscura/analyzers/packet/parser.py
oscura/analyzers/packet/payload.py
oscura/analyzers/packet/payload_analysis.py
oscura/analyzers/packet/payload_extraction.py
oscura/analyzers/packet/payload_patterns.py
oscura/analyzers/packet/stream.py
oscura/analyzers/patterns/__init__.py
oscura/analyzers/patterns/anomaly_detection.py
oscura/analyzers/patterns/clustering.py
oscura/analyzers/patterns/clustering_optimized.py
oscura/analyzers/patterns/discovery.py
oscura/analyzers/patterns/learning.py
oscura/analyzers/patterns/matching.py
oscura/analyzers/patterns/pattern_mining.py
oscura/analyzers/patterns/periodic.py
oscura/analyzers/patterns/reverse_engineering.py
oscura/analyzers/patterns/sequences.py
oscura/analyzers/power/__init__.py
oscura-0.8.0.dist-info/METADATA
oscura-0.8.0.dist-info/WHEEL
oscura-0.8.0.dist-info/entry_points.txt
oscura-0.8.0.dist-info/licenses/LICENSE
oscura-0.8.0.dist-info/RECORD
