Metadata-Version: 2.4
Name: oscura
Version: 0.8.0
Summary: Unified hardware reverse engineering framework. Extract all information from any system through signals and data. Unknown protocol discovery, state machine extraction, CRC recovery, security analysis. 16+ protocols, IEEE-compliant measurements.
Project-URL: Homepage, https://github.com/oscura-re/oscura
Project-URL: Documentation, https://github.com/oscura-re/oscura/tree/main/docs
Project-URL: Repository, https://github.com/oscura-re/oscura
Project-URL: Changelog, https://github.com/oscura-re/oscura/blob/main/CHANGELOG.md
Project-URL: Issue Tracker, https://github.com/oscura-re/oscura/issues
Project-URL: Discussions, https://github.com/oscura-re/oscura/discussions
License-Expression: MIT
License-File: LICENSE
Keywords: automotive-protocols,can-bus,crc-recovery,device-replication,embedded-systems,exploitation,hardware-reverse-engineering,hardware-security,i2c,ieee-compliance,logic-analyzer,obd-ii,oscilloscope,protocol-analysis,protocol-decoder,protocol-inference,reverse-engineering,right-to-repair,security-research,signal-analysis,spectral-analysis,spi,state-machine-learning,uart,unknown-protocol,vulnerability-analysis,waveform-analysis
Classifier: Development Status :: 3 - Alpha
Classifier: Intended Audience :: Developers
Classifier: Intended Audience :: Information Technology
Classifier: Intended Audience :: Science/Research
Classifier: Intended Audience :: Telecommunications Industry
Classifier: License :: OSI Approved :: MIT License
Classifier: Operating System :: OS Independent
Classifier: Programming Language :: Python :: 3
Classifier: Programming Language :: Python :: 3.12
Classifier: Programming Language :: Python :: 3.13
Classifier: Topic :: Scientific/Engineering
Classifier: Topic :: Scientific/Engineering :: Information Analysis
Classifier: Topic :: Security
Classifier: Topic :: System :: Hardware
Classifier: Topic :: System :: Hardware :: Hardware Drivers
Classifier: Typing :: Typed
Requires-Python: >=3.12
Requires-Dist: click<9.0.0,>=8.1.0
Requires-Dist: dpkt<2.0.0,>=1.9.0
Requires-Dist: numpy<3.0.0,>=1.24.0
Requires-Dist: pyyaml<7.0.0,>=6.0
Requires-Dist: scipy<2.0.0,>=1.10.0
Requires-Dist: tm-data-types<1.0.0,>=0.3.0
Requires-Dist: tqdm<5.0.0,>=4.65.0
Provides-Extra: all
Requires-Dist: asammdf<9.0.0,>=8.0.0; extra == 'all'
Requires-Dist: cantools<40.0.0,>=39.4.0; extra == 'all'
Requires-Dist: check-jsonschema<1.0.0,>=0.29.0; extra == 'all'
Requires-Dist: coverage[toml]<8.0.0,>=7.0; extra == 'all'
Requires-Dist: cryptography<47.0.0,>=44.0.1; extra == 'all'
Requires-Dist: h5py<4.0.0,>=3.0.0; extra == 'all'
Requires-Dist: hypothesis<7.0.0,>=6.0.0; extra == 'all'
Requires-Dist: interrogate<2.0.0,>=1.7.0; extra == 'all'
Requires-Dist: ipython<9.0.0,>=8.0.0; extra == 'all'
Requires-Dist: jinja2<4.0.0,>=3.1; extra == 'all'
Requires-Dist: jupyter<2.0.0,>=1.0.0; extra == 'all'
Requires-Dist: matplotlib<4.0.0,>=3.7.0; extra == 'all'
Requires-Dist: mypy<2.0.0,>=1.0; extra == 'all'
Requires-Dist: nbconvert!=7.16.6,<8.0.0,>=7.0.0; extra == 'all'
Requires-Dist: networkx<4.0.0,>=3.0; extra == 'all'
Requires-Dist: nptdms<2.0.0,>=1.7.0; extra == 'all'
Requires-Dist: openpyxl<4.0.0,>=3.0.0; extra == 'all'
Requires-Dist: pandas<3.0.0,>=2.0.0; extra == 'all'
Requires-Dist: pre-commit<5.0.0,>=4.0.0; extra == 'all'
Requires-Dist: psutil<7.0.0,>=5.9.0; extra == 'all'
Requires-Dist: pyserial<4.0.0,>=3.5; extra == 'all'
Requires-Dist: pytest-asyncio<1.0.0,>=0.23.0; extra == 'all'
Requires-Dist: pytest-benchmark<6.0.0,>=4.0.0; extra == 'all'
Requires-Dist: pytest-cov<8.0.0,>=6.0; extra == 'all'
Requires-Dist: pytest-randomly<4.0.0,>=3.0; extra == 'all'
Requires-Dist: pytest-rerunfailures<17.0,>=16.0; extra == 'all'
Requires-Dist: pytest-split<1.0.0,>=0.10.0; extra == 'all'
Requires-Dist: pytest-timeout<3.0.0,>=2.3.0; extra == 'all'
Requires-Dist: pytest-xdist<4.0.0,>=3.0; extra == 'all'
Requires-Dist: pytest<10.0.0,>=8.0; extra == 'all'
Requires-Dist: python-can<5.0.0,>=4.4.0; extra == 'all'
Requires-Dist: python-pptx<1.0.0,>=0.6.21; extra == 'all'
Requires-Dist: pyvisa-py<1.0.0,>=0.7.0; extra == 'all'
Requires-Dist: pyvisa<2.0.0,>=1.13.0; extra == 'all'
Requires-Dist: pywavelets<2.0.0,>=1.0.0; extra == 'all'
Requires-Dist: rapidfuzz<4.0.0,>=3.0.0; extra == 'all'
Requires-Dist: reportlab<6.0.0,>=4.4.7; extra == 'all'
Requires-Dist: rigolwfm<2.0.0,>=1.0.0; extra == 'all'
Requires-Dist: ruff<1.0.0,>=0.8.0; extra == 'all'
Requires-Dist: scapy<3.0.0,>=2.5.0; extra == 'all'
Requires-Dist: scikit-learn<2.0.0,>=1.3.0; extra == 'all'
Requires-Dist: types-pyyaml<7.0.0,>=6.0; extra == 'all'
Requires-Dist: yamllint<2.0.0,>=1.35; extra == 'all'
Provides-Extra: analysis
Requires-Dist: networkx<4.0.0,>=3.0; extra == 'analysis'
Requires-Dist: pywavelets<2.0.0,>=1.0.0; extra == 'analysis'
Requires-Dist: scikit-learn<2.0.0,>=1.3.0; extra == 'analysis'
Provides-Extra: automotive
Requires-Dist: asammdf<9.0.0,>=8.0.0; extra == 'automotive'
Requires-Dist: cantools<40.0.0,>=39.4.0; extra == 'automotive'
Requires-Dist: python-can<5.0.0,>=4.4.0; extra == 'automotive'
Requires-Dist: scapy<3.0.0,>=2.5.0; extra == 'automotive'
Provides-Extra: dataframes
Requires-Dist: openpyxl<4.0.0,>=3.0.0; extra == 'dataframes'
Requires-Dist: pandas<3.0.0,>=2.0.0; extra == 'dataframes'
Provides-Extra: dev
Requires-Dist: check-jsonschema<1.0.0,>=0.29.0; extra == 'dev'
Requires-Dist: coverage[toml]<8.0.0,>=7.0; extra == 'dev'
Requires-Dist: hypothesis<7.0.0,>=6.0.0; extra == 'dev'
Requires-Dist: interrogate<2.0.0,>=1.7.0; extra == 'dev'
Requires-Dist: mypy<2.0.0,>=1.0; extra == 'dev'
Requires-Dist: pre-commit<5.0.0,>=4.0.0; extra == 'dev'
Requires-Dist: pytest-asyncio<1.0.0,>=0.23.0; extra == 'dev'
Requires-Dist: pytest-benchmark<6.0.0,>=4.0.0; extra == 'dev'
Requires-Dist: pytest-cov<8.0.0,>=6.0; extra == 'dev'
Requires-Dist: pytest-randomly<4.0.0,>=3.0; extra == 'dev'
Requires-Dist: pytest-rerunfailures<17.0,>=16.0; extra == 'dev'
Requires-Dist: pytest-split<1.0.0,>=0.10.0; extra == 'dev'
Requires-Dist: pytest-timeout<3.0.0,>=2.3.0; extra == 'dev'
Requires-Dist: pytest-xdist<4.0.0,>=3.0; extra == 'dev'
Requires-Dist: pytest<10.0.0,>=8.0; extra == 'dev'
Requires-Dist: ruff<1.0.0,>=0.8.0; extra == 'dev'
Requires-Dist: types-pyyaml<7.0.0,>=6.0; extra == 'dev'
Requires-Dist: yamllint<2.0.0,>=1.35; extra == 'dev'
Provides-Extra: fuzzy
Requires-Dist: rapidfuzz<4.0.0,>=3.0.0; extra == 'fuzzy'
Provides-Extra: hardware
Requires-Dist: pyserial<4.0.0,>=3.5; extra == 'hardware'
Requires-Dist: pyvisa-py<1.0.0,>=0.7.0; extra == 'hardware'
Requires-Dist: pyvisa<2.0.0,>=1.13.0; extra == 'hardware'
Provides-Extra: hdf5
Requires-Dist: h5py<4.0.0,>=3.0.0; extra == 'hdf5'
Provides-Extra: iot
Requires-Dist: cryptography<47.0.0,>=44.0.1; extra == 'iot'
Provides-Extra: jupyter
Requires-Dist: ipython<9.0.0,>=8.0.0; extra == 'jupyter'
Requires-Dist: jupyter<2.0.0,>=1.0.0; extra == 'jupyter'
Requires-Dist: nbconvert!=7.16.6,<8.0.0,>=7.0.0; extra == 'jupyter'
Provides-Extra: oscilloscopes
Requires-Dist: nptdms<2.0.0,>=1.7.0; extra == 'oscilloscopes'
Requires-Dist: rigolwfm<2.0.0,>=1.0.0; extra == 'oscilloscopes'
Provides-Extra: reporting
Requires-Dist: jinja2<4.0.0,>=3.1; extra == 'reporting'
Requires-Dist: matplotlib<4.0.0,>=3.7.0; extra == 'reporting'
Requires-Dist: python-pptx<1.0.0,>=0.6.21; extra == 'reporting'
Requires-Dist: reportlab<6.0.0,>=4.4.7; extra == 'reporting'
Provides-Extra: standard
Requires-Dist: jinja2<4.0.0,>=3.1; extra == 'standard'
Requires-Dist: matplotlib<4.0.0,>=3.7.0; extra == 'standard'
Requires-Dist: openpyxl<4.0.0,>=3.0.0; extra == 'standard'
Requires-Dist: pandas<3.0.0,>=2.0.0; extra == 'standard'
Requires-Dist: psutil<7.0.0,>=5.9.0; extra == 'standard'
Requires-Dist: python-pptx<1.0.0,>=0.6.21; extra == 'standard'
Requires-Dist: reportlab<6.0.0,>=4.4.7; extra == 'standard'
Provides-Extra: system
Requires-Dist: psutil<7.0.0,>=5.9.0; extra == 'system'
Provides-Extra: visualization
Requires-Dist: matplotlib<4.0.0,>=3.7.0; extra == 'visualization'
